vacuum/__init__.py
vacuum/exceptions.py
vacuum/lint.py
vacuum/results.py
vacuum/util.py
vacuum/lib/__init__.py
vacuum/lib/vacuum
vacuum_openapi-0.2.0.dist-info/LICENSE
vacuum_openapi-0.2.0.dist-info/METADATA
vacuum_openapi-0.2.0.dist-info/WHEEL
vacuum_openapi-0.2.0.dist-info/top_level.txt
vacuum_openapi-0.2.0.dist-info/RECORD
