Metadata-Version: 2.1
Name: vacuum-openapi
Version: 0.2.0
Summary: Python bindings for the vacuum OpenAPI linting/validation Go library
License: MIT
Author: Zach Kanzler
Author-email: they4kman@gmail.com
Requires-Python: >=3.9,<4.0
Classifier: License :: OSI Approved :: MIT License
Classifier: Programming Language :: Python :: 3
Classifier: Programming Language :: Python :: 3.9
Classifier: Programming Language :: Python :: 3.10
Classifier: Programming Language :: Python :: 3.11
Classifier: Programming Language :: Python :: 3.12
Requires-Dist: orjson (>2.2.0,<4.0.0)
Requires-Dist: pydantic (>1.8.0,<3.0.0)
